MANIFEST.in
README.md
setup.cfg
setup.py
messaging_client/__init__.py
messaging_client/__main__.py
messaging_client/app.py
messaging_client/client_socket.py
messaging_client/messaging_client.py
messaging_client/metadata.py
messaging_client/option_parser.py
messaging_client.egg-info/PKG-INFO
messaging_client.egg-info/SOURCES.txt
messaging_client.egg-info/dependency_links.txt
messaging_client.egg-info/entry_points.txt
messaging_client.egg-info/top_level.txt
messaging_client/tests/__init__.py
messaging_client/tests/test_client_socket.py
messaging_client/tests/test_messaging_client.py