Metadata-Version: 1.0
Name: messaging-client
Version: 0.0.5
Summary: A simple message transport application and library.
Home-page: https://github.com/mjalas/messaging-client
Author: Mats Jalas
Author-email: mats.jalas@gmail.com
License: MIT
Keywords: message-transport
Platform: UNKNOWN
